yaproxy/DNSParser.py
yaproxy/DNSServer.py
yaproxy/DNSServerV2.py
yaproxy/GeventDNSServer.py
yaproxy/HTTPProxyServer.py
yaproxy/HTTPSProxyServer.py
yaproxy/ReverseHTTP.py
yaproxy/ReverseTCP.py
yaproxy/__init__.py
yaproxy/base.py
yaproxy/toproxy.py
yaproxy-0.0.1.dist-info/LICENSE
yaproxy-0.0.1.dist-info/METADATA
yaproxy-0.0.1.dist-info/WHEEL
yaproxy-0.0.1.dist-info/top_level.txt
yaproxy-0.0.1.dist-info/RECORD
