Metadata-Version: 2.1
Name: yaproxy
Version: 0.0.1
Summary: Yet Another Proxy
Home-page: https://github.com/linxiaohui/yaproxy
Author: Lin Xiao Hui
Author-email: llinxiaohui@126.com
License: UNKNOWN
Platform: UNKNOWN
Classifier: Programming Language :: Python :: 3
Classifier: License :: OSI Approved :: MIT License
Classifier: Operating System :: OS Independent
Requires-Python: >=3.6
